DecenTT/DecenTTErrors.py
DecenTT/__init__.py
DecenTT/client.py
DecenTT/IPFS/IPFSExceptions.py
DecenTT/IPFS/__init__.py
DecenTT/IPFS/config.py
DecenTT/IPFS/pubsub.py
DecenTT/IPFS/standard.py
DecenTT/IPFS/threader.py
DecenTT/IPFS/locales/IPFSLocalesExceptions.py
DecenTT/IPFS/locales/__init__.py
DecenTT/IPFS/locales/bootstrap.py
DecenTT/IPFS/locales/env_config.py
DecenTT/IPFS/logger/__init__.py
DecenTT/MQTT/MQTTErrors.py
DecenTT/MQTT/__init__.py
DecenTT/MQTT/client.py
DecenTT/MQTT/publisher.py
DecenTT/MQTT/subscriber.py
DecenTT/MQTT/logger/__init__.py
DecenTT/env/__init__.py
DecenTT/env/config.py
DecenTT/env/load_env.py
DecenTT/env/logger/__init__.py
DecenTT/logger/__init__.py
DecenTT-0.0.6.dist-info/LICENSE
DecenTT-0.0.6.dist-info/METADATA
DecenTT-0.0.6.dist-info/WHEEL
DecenTT-0.0.6.dist-info/top_level.txt
DecenTT-0.0.6.dist-info/RECORD
