Metadata-Version: 2.1
Name: DecenTT
Version: 0.0.6
Summary: Decentralized Telemetry Transport (DecenTT)
Home-page: https://github.com/saapo-ka-baadshah/DecenTT
Author: Amey Mahadik
Author-email: ameyarm@gmail.com
License: UNKNOWN
Project-URL: Bug Tracker, https://github.com/saapo-ka-baadshah/DecenTT/issues
Platform: UNKNOWN
Classifier: Programming Language :: Python :: 3
Classifier: License :: OSI Approved :: MIT License
Classifier: Operating System :: OS Independent
Requires-Python: >=3.6
License-File: LICENSE
Requires-Dist: certifi (==2021.10.8)
Requires-Dist: charset-normalizer (==2.0.8)
Requires-Dist: coloredlogs (==15.0.1)
Requires-Dist: humanfriendly (==10.0)
Requires-Dist: idna (==3.3)
Requires-Dist: ipfs-api (==0.2.3)
Requires-Dist: paho-mqtt (==1.6.1)
Requires-Dist: python-dotenv (==0.19.2)
Requires-Dist: requests (==2.26.0)
Requires-Dist: six (==1.16.0)
Requires-Dist: tqdm (==4.62.3)
Requires-Dist: urllib3 (==1.26.7)
Requires-Dist: wget (==3.2)
